[
  {
    "title": "Инженер по QA/тестировщик",
    "link": "https://hh.ru/vacancy/121971409?query=Python&hhtmFrom=vacancy_search_list",
    "company": "ООО Хелоу",
    "salary": "Зарплата не указана",
    "source": "hh"
  },
  {
    "title": "Web разработчик middle",
    "link": "https://hh.ru/vacancy/122066781?query=Python&hhtmFrom=vacancy_search_list",
    "company": "ПАО МГКЛ",
    "salary": "Зарплата не указана",
    "source": "hh"
  },
  {
    "title": "Аналитик данных/Data Analyst/BI-аналитик",
    "link": "https://hh.ru/vacancy/121928488?query=Python&hhtmFrom=vacancy_search_list",
    "company": "ЭстэйтЛига",
    "salary": "Зарплата не указана",
    "source": "hh"
  },
  {
    "title": "Экономист/Аналитик",
    "link": "https://hh.ru/vacancy/121279512?query=Python&hhtmFrom=vacancy_search_list",
    "company": "Allianz Partners",
    "salary": "Зарплата не указана",
    "source": "hh"
  },
  {
    "title": "Site Reliability Engineer (SRE)/Sysadmin junior",
    "link": "https://hh.ru/vacancy/104344551?query=Python&hhtmFrom=vacancy_search_list",
    "company": "ABCP",
    "salary": "Зарплата не указана",
    "source": "hh"
  },
  {
    "title": "Аналитик по промо и CRM",
    "link": "https://hh.ru/vacancy/120461826?query=Python&hhtmFrom=vacancy_search_list",
    "company": "ECCO",
    "salary": "Зарплата не указана",
    "source": "hh"
  },
  {
    "title": "Тимлид команды разработки виртуальных рабочих столов VDI",
    "link": "https://hh.ru/vacancy/121955908?query=Python&hhtmFrom=vacancy_search_list",
    "company": "ООО Хелоу",
    "salary": "Зарплата не указана",
    "source": "hh"
  },
  {
    "title": "Преподаватель программирования (Python, С++, С#)",
    "link": "https://hh.ru/vacancy/120919613?query=Python&hhtmFrom=vacancy_search_list",
    "company": "АНО ДО Московская школа программистов",
    "salary": "Зарплата не указана",
    "source": "hh"
  },
  {
    "title": "TeamLead",
    "link": "https://hh.ru/vacancy/118765841?query=Python&hhtmFrom=vacancy_search_list",
    "company": "ООО HeadHunter::Backend",
    "salary": "Зарплата не указана",
    "source": "hh"
  },
  {
    "title": "Руководитель направления (автоматизация риск-отчетности ВПОДК)",
    "link": "https://hh.ru/vacancy/121879366?query=Python&hhtmFrom=vacancy_search_list",
    "company": "АО Азиатско-Тихоокеанский Банк",
    "salary": "Зарплата не указана",
    "source": "hh"
  }
]